{
  "posts": [
    {
      "town": "Chicago",
      "age": "57",
      "careerPpg": "30",
      "draftYear": "1984",
      "championships": "6",
      "mvp": "5",
      "origin": "Brooklyn",
    },
    {
      "town": "San Francisco",
      "age": "32",
      "careerPpg": "23",
      "draftYear": "2009",
      "championships": "3",
      "mvp": "2",
      "origin": "Akron",
    },
   {
      "town": "Los Angeles",
      "age": "37",
      "careerPpg": "27",
      "draftYear": "2003",
      "championships": "3",
      "mvp": "3",
      "origin": "Akron",
    },
    {
      "town": "Boston",
      "age": "63",
      "careerPpg": "24",
      "draftYear": "1980",
      "championships": "3",
      "mvp": "3",
      "origin": "Indiana",
    }	
 ]
}
